MANIFEST.in
README.rst
setup.py
collective/.DS_Store
collective/__init__.py
collective/__init__.pyc
collective.ptg.garagedoor.egg-info/PKG-INFO
collective.ptg.garagedoor.egg-info/SOURCES.txt
collective.ptg.garagedoor.egg-info/dependency_links.txt
collective.ptg.garagedoor.egg-info/entry_points.txt
collective.ptg.garagedoor.egg-info/namespace_packages.txt
collective.ptg.garagedoor.egg-info/not-zip-safe
collective.ptg.garagedoor.egg-info/requires.txt
collective.ptg.garagedoor.egg-info/top_level.txt
collective/ptg/.DS_Store
collective/ptg/__init__.py
collective/ptg/__init__.pyc
collective/ptg/garagedoor/.DS_Store
collective/ptg/garagedoor/__init__.py
collective/ptg/garagedoor/__init__.pyc
collective/ptg/garagedoor/configure.zcml
collective/ptg/garagedoor/garagedoor.pt
collective/ptg/garagedoor/i18n.sh
collective/ptg/garagedoor/resources/.DS_Store
collective/ptg/garagedoor/resources/no_style.css
collective/ptg/garagedoor/resources/style.css
collective/ptg/garagedoor/resources/styleII.css
docs/HISTORY.txt
docs/INSTALL.txt
docs/LICENSE.GPL
docs/LICENSE.txt