Metadata-Version: 1.0
Name: collective.ptg.garagedoor
Version: 0.1
Summary: garagedoor for plonetruegallery
Home-page: https://github.com/collective/collective.ptg.garagedoor
Author: Espen Moe-Nilssen
Author-email: espen@medialog.no
License: GPL
Keywords: plonetruegallery gallery plone addon
Platform: UNKNOWN
Classifier: Framework :: Plone
Classifier: Programming Language :: Python
